sixth/__init__.py
sixth/schemas.py
sixth/sdk.py
sixth/middlewares/__init__.py
sixth/middlewares/encryption_middleware.py
sixth/middlewares/six_base_http_middleware.py
sixth/middlewares/six_independent_rate_limiter.py
sixth/middlewares/six_rate_limiter_middleware.py
sixth/middlewares/six_secure_logs_rate_limiter.py
sixth/pen_test/__init__.py
sixth/pen_test/auto_pen_test.py
sixth/utils/__init__.py
sixth/utils/encryption_utils.py
sixth/utils/gen.py
sixth/utils/pickle_db_with_lock.py
sixth/utils/time_utils.py
sixth_python-0.2.6.3.dist-info/LICENSE
sixth_python-0.2.6.3.dist-info/METADATA
sixth_python-0.2.6.3.dist-info/WHEEL
sixth_python-0.2.6.3.dist-info/top_level.txt
sixth_python-0.2.6.3.dist-info/RECORD
