Metadata-Version: 2.1
Name: sixth-python
Version: 0.2.6.3
Summary: Sixth offical python package
Home-page: UNKNOWN
Author: 6thSense
Author-email: tech@withsix.co
License: UNKNOWN
Keywords: python,cybersecurity,pentesting,encryption,rate limiting,xss prevention
Platform: UNKNOWN
Classifier: Development Status :: 3 - Alpha
Classifier: Intended Audience :: Developers
Classifier: Programming Language :: Python :: 3
Classifier: Operating System :: Unix
Classifier: Operating System :: MacOS :: MacOS X
Classifier: Operating System :: Microsoft :: Windows
Requires-Dist: aes-everywhere
Requires-Dist: annotated-types
Requires-Dist: anyio
Requires-Dist: bleach
Requires-Dist: BTrees
Requires-Dist: CacheControl
Requires-Dist: cachetools
Requires-Dist: certifi
Requires-Dist: cffi
Requires-Dist: charset-normalizer
Requires-Dist: click
Requires-Dist: crypto
Requires-Dist: cryptography
Requires-Dist: dnspython
Requires-Dist: docutils
Requires-Dist: ecdsa
Requires-Dist: exceptiongroup
Requires-Dist: fastapi
Requires-Dist: fastapi-versioning
Requires-Dist: firebase-admin
Requires-Dist: google-api-core
Requires-Dist: google-api-python-client
Requires-Dist: google-auth
Requires-Dist: google-auth-httplib2
Requires-Dist: google-cloud-core
Requires-Dist: google-cloud-firestore
Requires-Dist: google-cloud-storage
Requires-Dist: google-crc32c
Requires-Dist: google-resumable-media
Requires-Dist: googleapis-common-protos
Requires-Dist: grpcio
Requires-Dist: grpcio-status
Requires-Dist: h11
Requires-Dist: httplib2
Requires-Dist: idna
Requires-Dist: importlib-metadata
Requires-Dist: importlib-resources
Requires-Dist: jaraco.classes
Requires-Dist: keyring
Requires-Dist: markdown-it-py
Requires-Dist: mdurl
Requires-Dist: more-itertools
Requires-Dist: msgpack
Requires-Dist: Naked
Requires-Dist: passlib
Requires-Dist: persistent
Requires-Dist: pickleDB
Requires-Dist: pkginfo
Requires-Dist: proto-plus
Requires-Dist: protobuf
Requires-Dist: pyasn1
Requires-Dist: pyasn1-modules
Requires-Dist: pycparser
Requires-Dist: pycryptodome
Requires-Dist: pycryptodomex
Requires-Dist: pydantic ==1.10.9
Requires-Dist: pydantic-core
Requires-Dist: Pygments
Requires-Dist: PyJWT
Requires-Dist: pyngrok
Requires-Dist: pyparsing
Requires-Dist: python-dotenv
Requires-Dist: python-nmap
Requires-Dist: pytz
Requires-Dist: PyYAML
Requires-Dist: readme-renderer
Requires-Dist: requests
Requires-Dist: requests-toolbelt
Requires-Dist: rfc3986
Requires-Dist: rich
Requires-Dist: rsa
Requires-Dist: shellescape
Requires-Dist: six
Requires-Dist: sniffio
Requires-Dist: starlette
Requires-Dist: tinydb
Requires-Dist: transaction
Requires-Dist: twine
Requires-Dist: typing-extensions
Requires-Dist: uritemplate
Requires-Dist: urllib3
Requires-Dist: uvicorn
Requires-Dist: webencodings
Requires-Dist: zc.lockfile
Requires-Dist: ZConfig
Requires-Dist: zipp
Requires-Dist: ZODB
Requires-Dist: zodbpickle
Requires-Dist: zope.interface
